__init__.py
porkbun_api.py
porkbun_api-2.0.0.dist-info/LICENSE
porkbun_api-2.0.0.dist-info/METADATA
porkbun_api-2.0.0.dist-info/WHEEL
porkbun_api-2.0.0.dist-info/top_level.txt
porkbun_api-2.0.0.dist-info/RECORD
