Metadata-Version: 2.2
Name: porkbun-api
Version: 2.0.0
Summary: A Python wrapper for Porkbun API with extra features and shortcuts
Author-email: mazer <contact@m3r.one>
Project-URL: Homepage, https://github.com/m3rone/porkbun-api
Project-URL: Bug Tracker, https://github.com/m3rone/porkbun-api/issues
Classifier: Programming Language :: Python :: 3
Classifier: License :: OSI Approved :: MIT License
Classifier: Operating System :: OS Independent
Requires-Python: >=3.10
License-File: LICENSE
Requires-Dist: certifi==2024.7.4
Requires-Dist: charset-normalizer==3.3.2
Requires-Dist: idna==3.7
Requires-Dist: requests==2.32.2
Requires-Dist: urllib3==2.2.2
